Workbook

Sheet Pipeline
A1: Date | B1: Brand Name | C1: Type of Scope | D1: Handled by | E1: POC Name | F1: Phone | G1: Email | H1: Stage | I1: Costs | J1: Proposal Date/Follow up | K1: Status
B2: Food Brand Launch | C2: Branding | D2: Tan | E2: Akshay | F2: +91 98338 14029 | H2: Didnt work out | I2: - | K2: Didnt work out because of costs.
B3: The Premium Basket | C3: Branding | D3: Ally | E3: Ebrahim Kothari | F3: +91 88281 92685 | G3: ebrahim@thepremiumbasket.com | H3: Didnt work out | I3: 167500000 | K3: We've shared the signed NDA with the client
B4: Miss Claire | C4: Branding | D4: Ally | E4: Mallika Ahar | F4: Not available | H4: Didnt work out | I4: 122500000 | K4: SPOC has been unresponsive.
B5: Raindus Beauty Care | C5: Branding | D5: Ally | E5: Saumya | F5: +91 78019 04359 | G5: admin@eurekacosmo.com | H5: Didnt work out | I5: 122500000 | K5: Branding proposal shared.
B6: Multichem | C6: Branding | D6: Ally | E6: Sejal Jadiyar | F6: +91 77382 47802 | G6: hello@multichemindia.com | H6: Didnt work out | I6: 74500000 | K6: Awaiting an update from the founder.
B7: Restaurant | C7: Branding | D7: Ally | E7: Ashwin | F7: +91 73027 39698 | G7: ashwin2002singh@gmail.com | H7: Closed | I7: 120000000 | K7: Closed. Awaiting advance payment, client has mentioned that is in process.
B8: Bongchie | C8: Branding | D8: Ally | E8: Tushar | F8: +91 94547 48677 | G8: tushar@bongchie.com | H8: Didnt work out | I8: 140000000 | K8: Follow up done on the 1st July. No response. Awaiting a response.
B9: Sweet Dreams | C9: Branding | D9: Ally | E9: Khushi | F9: +91 98709 10111 | G9: khushi.apwig@gmail.com | H9: Closed | I9: 100000000 | K9: Contract needs to be shared
B10: KSM Ashwagandha | C10: Branding, Web | D10: Tan | E10: Kartikeya | F10: +91 98490 30798 | G10: kartikeya@ixoreal.com | H10: Closed | I10: 32500000 | K10: Project completed.
B11: Welspun | C11: Branding | D11: Ally | E11: Alok | F11: +91 99980 03155 | G11: Alok_Bhinde@welspun.com | H11: Didnt work out | K11: Client has said that CMO is travelling and this will take sometime to close on.
B12: Un'layered | C12: Branding | D12: Ally | E12: Bhawna | F12: +91 95282 55005 | G12: bhawnasharmaofficial@gmail.com | H12: Didnt work out | I12: 100000000 | K12: Call to be made on 2nd July 2025.
B13: Nilambari Sarees | C13: Branding, Web | D13: Tan | E13: Pranav | F13: +91 88004 77886 | G13: pranavnilambari@gmail.com | H13: Commercials | I13: 120000000 | K13: He ghosted us.
B14: Stationery Brand | C14: Branding | D14: Ally | E14: Radhika | F14: +91 88894 44400 | G14: radhika@krishnaunited.com | H14: Closed | I14: 50000000 | K14: Branding proposal closed.
B15: CtrlS | C15: Branding | D15: Ally | E15: Pragun | F15: +91 93729 10823 | G15: pragun.narang@ctrls.in | H15: Commercials | I15: 350000000 | K15: Client will update us on 14th August since he is on leave.
B16: Switchback | C16: Branding | D16: Ally | E16: Anushri | F16: +91 98198 77308 | G16: anushri20@gmail.com | H16: Commercials | I16: 150000000 | K16: This is cold atm
B17: Ride Glyde | C17: Branding | D17: Ally | E17: Vignesh | F17: +91 91369 60544 | G17: vignesh@rideglyde.in | H17: Commercials | I17: 150000000 | K17: Client pushing marketing a bit for now, focusing on finalising operations.
B18: Kimirica | C18: Branding | D18: Ally | E18: Saomya | F18: +91 98930 60926 | G18: soamya.mital@kimirica.com | H18: Commercials | I18: 150000000 | K18: On hold atm
B19: Messe Muenchen | C19: Branding | D19: Ally | E19: Riddhi | F19: +91 75179 98999 | G19: support.marcom@mm-india.in | H19: Didnt work out | I19: 180000000 | K19: Client is not responding
B20: Vanveda Organics | C20: Branding | D20: Ally | E20: Chandan | F20: +91 75179 98999 | G20: support.marcom@mm-india.in | H20: Didnt work out | I20: 85000000 | K20: Update to be received by this weekend. 9-10th August
B21: Pepsodent | C21: Branding | D21: Tan | E21: Reshma | F21: +91 99302 99445 | G21: reshma.vaidya@unilever.com | H21: Closed | I21: 100000000 | K21: Project completed.
B22: Zydus Cadila | C22: Branding | D22: Tan | E22: Yash | F22: +91 98697 31997 | G22: YASHL.GANDHI@zyduslife.com | H22: Didnt work out | I22: 70000000 | K22: They ghosted us.
B23: Unomax | C23: Branding | D23: Ally | E23: Sajad | G23: sajjad.godhrawala@unomaxpens.com | H23: Didnt work out | I23: 50000000 | K23: Closed on an industrial design agency
B24: Sports Nutrition Brand | C24: Branding | D24: Ally | E24: Shabnam | F24: +91 97268 82211 | G24: Shabnamhalani8@gmail.com | H24: Commercials | I24: 115000000 | K24: Follow up done client will get back post the long weekend
B25: Speedex | C25: Branding | D25: Ally | E25: Dewakar | F25: +91 99112 02317 | G25: brandmarketer@speedexind.com | H25: Commercials | I25: 100000000 | K25: Pitch on 26th August
B26: Scapes Hospitality | C26: SMM, Web | D26: Tan | E26: Aastha | F26: +91 81300 01729 | G26: aastha@scapeshospitality.com | H26: Commercials | K26: Project was on hold.
B27: Cafe Branding | C27: Branding | D27: Ally | E27: Sharon | F27: +91 99306 56794 | G27: sharon22193@gmail.com | H27: Didnt work out | I27: 50000000 | K27: Branding proposal shared. Client is reviewing it at their end
B28: Horizon Tech Park | C28: Coffee table Book | D28: Ally | G28: ronnie.Zaiwalla@hiparks.com | I28: 50000000 | K28: Branding proposal and references shared for the brochure.
B29: HOF | C29: Branding | D29: Ally | E29: Somendra | F29: +91 99043 04513 | G29: somendra@hofindia.com | H29: Didnt work out | I29: 90000000 | K29: Branding proposal shared. Client is reviewing it at their end
B30: South Indian Restaurant | C30: Branding | D30: Ally | E30: Shashank | F30: +91 88252 02574 | G30: shashanksauravv@gmail.com | H30: Didnt work out | I30: TBD | K30: Client will call back
B31: Pantaloons | C31: Branding | D31: Ally | E31: Namit | F31: +91 88795 02010 | G31: namit.jaiswal@abfrl.adityabirla.com | H31: Pitch | I31: TBD | K31: Rate card has been shared with the client. Client to get back
B32: XOBO | C32: Branding | D32: Ally | E32: Kunal | F32: +91 99601 00100 | G32: kunaljain.vega@gmail.com | H32: Pitch | K32: Proposal under review.
B33: Indo Atma | C33: Branding | D33: Ally | E33: Arastu | F33: +5617597364 | G33: arastu@indoatma.com | H33: Didnt work out | K33: Client has gone silent on the NDA front.
B34: Komyo Wellness | C34: Web | D34: Ally | E34: Aditi | F34: +91 98110 29230 | G34: aditi@Komyo.in | H34: Commercials | K34: Client to get back on the proposal
B35: KKings Events | C35: Branding | D35: Ally | E35: Ketan | G35: ketan@kkingsevents.com | H35: Commercials | I35: 130000000 | K35: Proposal shared client to revert on the same.
B36: Kaafi Machine | C36: Branding | D36: Ally | E36: Anurag | G36: anurag.das@kaapimachines.com | H36: Pitch | I36: TBD | K36: Anurag to get back on the call timing
B37: House of Swadehi | C37: Branding | D37: Ally | G37: houseofswadeshiofficial@gmail.com | H37: First Call | I37: TBD | K37: Have requested for a call time to discuss the Logo development project.
B38: Saanya | C38: Web | D38: Ally | F38: +91 93100 00663 | G38: saanyabjain@gmail.com | H38: First Call | I38: TBD | K38: She wants to see the backend work on the developer
B39: Ruloans | C39: Campaign | D39: Ally | E39: Shikha | G39: shikha.mehta@ruloans.com | H39: Commercials | I39: TBD | K39: In-person meet at the client office
B40: Humane World For Animals | C40: Creatives | D40: Ally | E40: Shreya | F40: +91 63589 13490 | G40: sswaminath@humaneworld.org | H40: First Call | I40: TBD | K40: revised proposal to be shared for print and outdoor
B41: Anahata | D41: Ally | E41: Cecilia | F41: +91 98205 33332 | G41: admin@anahata.in | H41: First Call | K41: she will call back
B42: Hamleys Cafe | C42: Campaign | D42: Ally | E42: Bala | F42: +91 98209 64012 | G42: sivaraman.B@ril.com | H42: Closed | I42: 20000000 | K42: Hamleys Cafe Logo and Guidelines
B43: Sambhav Group | C43: Web | D43: Tan | E43: Megha | F43: +91 90049 86631 | G43: media@sambhavgroup.co.in | H43: Commercials | K43: Project was on hold.
B44: Cool Planet | C44: Branding | D44: Ally | E44: Rizqi | F44: +94777653936 | G44: qi@coolplanet.lk | H44: Commercials | I44: TBD
B45: Voltas | C45: Branding | D45: Tan | E45: Gayathri | F45: +91 96006 56773 | G45: gayathrinarendran@voltas.com | H45: First Call | K45: Client ghosted us.
B46: A Class Marble | C46: Web | D46: Tan | E46: Shivani | F46: +91 72900 73527 | G46: branding@aclassmarble.co.in | H46: Commercials | K46: Project on hold
B47: Dynamic Engineering | C47: Branding | D47: Ally | E47: Sehej | F47: +91 99305 64146 | G47: info@dynamicengineeringcompany.com | H47: Didnt work out | K47: Cost of 3L
B48: Rameswaram cafe | C48: Branding | D48: Tan | E48: Pooja | F48: +91 89281 91088 | G48: pooja.u@seabird.co.in | H48: Commercials | K48: They ghosted us.
B49: Sony Music | C49: Branding | D49: Ally | E49: Samarth | F49: +91 77220 36793 | G49: samarth.manocha@sonymusic.com | H49: Commercials | K49: Proposal shared. Client to get back
B50: ECCO | C50: Branding | D50: Ally | E50: Inza | F50: +91 96193 40027 | G50: INN@ecco.com | H50: Commercials | K50: Revised proposal discussion to happen basis the deliverables requested by the client.
B51: Upadhyaya Foundation | C51: Branding | D51: Ally | E51: Preetham | F51: +91 94837 80058 | G51: preetham@upadhyayafoundation.org | H51: Commercials | K51: Proposal shared with the client.
B52: Ice Cream Brand | C52: Branding | D52: Ally | E52: Dharmesh | F52: +91 79074 87352 | G52: hnmpltd@outlook.com | H52: Didnt work out | K52: Budget of 2L
B53: Dainik Bhaskar Pet Care | C53: Branding | D53: Tan | E53: Diva | F53: - | G53: diva@dbdigital.in | H53: First Call | K53: Ghosted us because of commercials I guess
B54: Dove | C54: Branding | D54: Tan | E54: Manasee | F54: +91 98676 42764 | G54: manasee.naik@unilever.com | H54: Closed | I54: 15000000 | K54: Project completed
B55: Pears | C55: Branding | D55: Tan | E55: Manasee | F55: +91 98676 42764 | G55: manasee.naik@unilever.com | H55: Closed | I55: 15000000 | K55: Project completed
B56: Everfruit | C56: Branding | D56: Ally | E56: Piyush | F56: +91 95616 21164 | G56: piyush.parakh@everfruit.in | H56: Commercials | K56: Proposal shared with the client.
B57: Hindustan Times | C57: Branding | D57: Ally | E57: Srashti | F57: +91 87178 78891 | G57: srashti.jain@hindustantimes.com | H57: Didnt work out | K57: Badge and Trophy design costing shared with the client.
B58: Big FM | C58: Branding | D58: Ally | E58: Soha | F58: +91 99905 90444 | G58: akanksha.goel@weinvert.com | H58: Commercials | K58: RFP shared with the client.
B59: Amaya | C59: Web | D59: Ally | E59: Akshi | F59: +91 96431 22358 | G59: aakshi.katyal@gmail.com | H59: Commercials | K59: Proposal and pitch for the 24th October.
B60: Peruh | C60: Branding | D60: Tan | E60: Prerna | G60: prerna@peruhworld.com | H60: First Call | K60: Ghosted us
B61: Pump Manufacturer | C61: Branding | D61: Ally | E61: Nik | F61: +3468528114 | G61: nikp09528@gmail.com | H61: Didnt work out | K61: CTR on the proposal shared
B62: Jawa | C62: Branding | D62: Ally | E62: Samir Gokhale | F62: +91 99210 03800 | G62: gokhale.samir@classiclegends.com | H62: First Call | K62: Blueprint to be shared with the client basis the last pitch
B63: Volfsbane | C63: Web | D63: Ally | E63: Mansi | G63: mansi@volfsbane.com | H63: Commercials | K63: Website branding proposal shared. Awaiting response.
B64: Haldirams | C64: Branding | D64: Ally | E64: Bhagyashree | F64: +91 96193 42495 | G64: bhagyashree.paralkar@haldirams.com | H64: Didnt work out | K64: Proposal to be shared post closure on social media
B65: Asian Star | C65: Branding | D65: Ally | E65: Ryan | F65: +91 98205 07257 | G65: ryan@asianstargroup.com | H65: First Call | K65: CTR back on the proposal shared
B66: Samarya | C66: Branding | D66: Ally | E66: Aryan | F66: +91 91378 09177 | G66: aryan.ruia@samaryamedia.com | H66: Commercials | K66: Logo Design Proposal shared with the client.
B67: Seedwater | C67: Branding | D67: Ally | E67: Vivek | F67: +91 98197 11218 | G67: vivek@seedwtr.com | H67: Commercials | K67: CTR on the proposal shared
B68: Quartroloom | C68: Branding | D68: Ally | E68: Avase | F68: +91 88676 58800 | G68: avase@quartoloom.com | H68: Commercials | K68: CTR on the proposal shared
B69: Rajhem Jewellers | C69: Branding | D69: Ally | E69: Ritik | F69: +91 95153 11755 | G69: ritikjain23112@gmail.com | H69: Commercials | K69: CTR on the proposal shared
B70: Wellness Brand | C70: Branding | D70: Ally | E70: Ruchi | F70: +91 73508 89295 | G70: ruchi.pandit2008@gmail.com | H70: Commercials | K70: Client will get back with the numbers they want to close on today.
B71: O Source Global | C71: Web | D71: Tan | E71: Durvanka | F71: +91 96194 33680 | G71: durvanka.murkute@osourceglobal.com | H71: Commercials | K71: Commercials didn't work
B72: EuroKids | C72: Web | D72: Tan | E72: Rakesh | F72: +91 97737 73230 | G72: rakesh.baikar@lighthouse-learning.com | H72: Commercials | K72: Ghosted us
B73: Sanjeev (Healthy Snacks) | C73: Branding | D73: Ally | E73: Sanjeev | F73: +91 98153 38888 | G73: sb@sbhind.com | H73: First Call | K73: Proposal under review.
B74: Worthvial | C74: Branding | D74: Ally | E74: Rohit | F74: +91 90132 32346 | G74: rohit@worthvial.com | H74: Commercials | K74: Client will get back with the numbers they want to close on today.
B75: Bellagio | C75: Branding | D75: Ally | E75: Arya | F75: +91 90132 32346 | G75: aryaadak2000@gmail.com | H75: Commercials | K75: Client meeting on the 12th Jan, 2026
... B77: Nuvoco | C77: Branding | D77: Ally | E77: Nikhil | F77: +91 97020 36462 | G77: Nikhil.Sukthankar@nuvoco.com | H77: Pitch | K77: Pitch done. RFQ will be shared with us this week.
B78: Kids Infotainment | C78: Branding | D78: Tan | E78: Mazahir | F78: +91 90221 22928 | H78: First Call | K78: He ghosted us
B79: Zune Clothing | C79: Branding | D79: Tan | E79: Shivam | F79: +91 75056 43933 | G79: shivamyadav9258@gmail.com | H79: Didnt work out | K79: Had very low budgets, 2L for branding.
B80: Luxury Bags | C80: Branding | D80: Ally | E80: Ayesha | F80: +91 96190 77701 | G80: NA | H80: Didnt work out | K80: Low budget client.
B81: HOS Global Foods | C81: Branding | D81: Ally | E81: Shruti | F81: +91 88794 33104 | G81: skulkarni@houseofspicesindia.com | H81: Didnt work out | K81: Client has mentioned they will work on future projects with us.
B82: Els Hair | C82: Web | D82: Ally | E82: Simran | F82: +91 83830 08876 | G82: work.skataria@gmail.com | H82: Didnt work out | K82: No response post proposal for website revamp shared with the client.
B83: Ageasy | C83: Branding | D83: Ally | E83: Arushi | F83: +91 90134 92656 | G83: arushi.aggarwal@antaraseniorcare.com | H83: Closed | I83: 40000000 | K83: Proposal shared with the client for review and approval
B84: Cello | C84: Branding | D84: Ally | E84: Suresh | G84: suresh.amarnani@celloworld.com | H84: Commercials | K84: Proposal has been shared. No response.
B85: Inorbit | C85: Branding | D85: Ally | E85: Tiyasha | F85: +91 96741 19228 | G85: tiyasha.mitra@inorbit.in | H85: Didnt work out | K85: Case Studies deck shared with the client.
A86: 14th Jan | B86: HueTag | C86: Branding | D86: Tan | E86: Yash | F86: +91 96436 34608 | G86: Yash.lakhmani0580@gmail.com | H86: First Call | K86: commercials didn't work
A87: 19th Jan | B87: Oral-care FMCG brand | C87: Branding | D87: Ally | E87: Harshleen | F87: +91 95751 00999 | G87: bhatiaharshleen11@gmail.com | H87: Didnt work out | I87: TBD | K87: Client has not responded to calls and texts.
B88: Elevator Brand | C88: Branding | D88: Ally | E88: Prachi | F88: +91 77383 87212 | G88: prachi.jadhav@eroselevators.com | H88: Didnt work out | I88: TBD | K88: Commercials shared with the client. Client has not responded thereafter.
A89: 22nd Jan | B89: Project Ezza | C89: Branding, Web | D89: Ally | E89: Dimpy | F89: +91 99202 74266 | H89: Commercials | I89: 550000 | K89: Proposal has been shared with the client for website.
A90: 28th Jan | B90: My Athlete | C90: Branding | D90: Ally | E90: Bhaben | F90: +91 97926 74222 | G90: bhaben83@gmail.com | H90: Didnt work out | I90: TBD | K90: Proposal to be shared for the same by the 29th January, 2026
B91: Forge Tech | C91: Branding | D91: Ally | E91: Prasad | F91: +91 72084 82730 | G91: prasad.kabadi@ideaforgetech.com | H91: First Call | I91: TBD | K91: Tried connecting with the client but was not able to get through.
B92: Punjas | C92: Branding | D92: Ally | E92: Gopal | F92: +91 67970 08805 | G92: gopal@punjas.com | H92: Commercials | K92: Rate card shared with the client.
B93: NA | C93: Branding | D93: Tan | E93: Falguni | F93: +91 88799 27537 | G93: falguni240396@gmail.com | H93: Commercials | K93: commercials didn't work
B94: Biorad | C94: Branding | D94: Ally | E94: Tanishq | F94: +610451991409 | G94: tanishq.hegde@bioradmedisys.com | H94: First Call | K94: Proposal commercials closure call at 1 pm.
A95: 29th Jan | B95: Pureforma | C95: Branding | D95: Ally | E95: Pratima | F95: +91 98929 02338 | G95: pratima.kamat@pureforma.in | H95: First Call | K95: First call done with the client.
B96: Oilmax | C96: Branding | D96: Ally | E96: Rostan | F96: +91 99602 87807 | G96: rostan.miranda@aniritventures.com | H96: Commercials | K96: Proposal has been shared with the client. Awaiting response on the same.
B97: Kimora | C97: Branding | D97: Ally | E97: Bhumi | F97: +91 95100 70153 | G97: business@kimora.in | H97: Commercials | K97: Internal review of budgets ongoing.
A98: 12th Feb | B98: Organic Food Brand | C98: Branding | D98: Tan | E98: Yashraj | F98: +91 96986 91111 | G98: yashrajsinghtada@gmail.com | H98: First Call | I98: 100000000 | K98: Yashraj has a budget of 7L for branding and packaging.
A99: 12th Feb | B99: Coffee Branding | C99: Branding | D99: Tan | E99: Shreyansh | F99: +91 99872 48272 | G99: doshi.shreyansh@gmail.com | H99: Commercials | K99: Sent him a proposal for 22L, awaiting to hear back
A100: 16th Feb | B100: Automobile brand | C100: Branding | D100: Tan | E100: Dhrumil | F100: +91 91670 76010 | G100: dhrumil@dhcindia.com | H100: Commercials | K100: Have sent him our commercials
A101: 17th Feb | B101: SBI MF | C101: Creatives | D101: Tan | E101: Prachi | F101: +91 95994 07143 | G101: prachi.shinde@sbimf.com | H101: First Call
...

Sheet Dashboard
A1: PIPELINE DASHBOARD
A2: Formulas update automatically when Pipeline data changes
A4: PIPELINE SUMMARY BY STAGE
A5: Stage | B5: Count | C5: Total Value | D5: Avg Deal Size
A6: First Call | B6: =COUNTIF(Pipeline!H:H,"First Call") | C6: =SUMIF(Pipeline!H:H,"First Call",Pipeline!I:I) | D6: =IFERROR(C6/B6,0)
A7: Pitch | B7: =COUNTIF(Pipeline!H:H,"Pitch") | C7: =SUMIF(Pipeline!H:H,"Pitch",Pipeline!I:I) | D7: =IFERROR(C7/B7,0)
A8: Commercials | B8: =COUNTIF(Pipeline!H:H,"Commercials") | C8: =SUMIF(Pipeline!H:H,"Commercials",Pipeline!I:I) | D8: =IFERROR(C8/B8,0)
A9: Closed | B9: =COUNTIF(Pipeline!H:H,"Closed") | C9: =SUMIF(Pipeline!H:H,"Closed",Pipeline!I:I) | D9: =IFERROR(C9/B9,0)
A10: Didnt work out | B10: =COUNTIF(Pipeline!H:H,"Didnt work out") | C10: =SUMIF(Pipeline!H:H,"Didnt work out",Pipeline!I:I) | D10: =IFERROR(C10/B10,0)
A11: TOTAL | B11: =SUM(B6:B10) | C11: =SUM(C6:C10) | D11: =IFERROR(C11/B11,0)
A13: REVENUE METRICS
A14: Closed Revenue | B14: =SUMIF(Pipeline!H:H,"Closed",Pipeline!I:I)
A15: Active Pipeline Value | B15: =SUMIF(Pipeline!H:H,"First Call",Pipeline!I:I)+SUMIF(Pipeline!H:H,"Pitch",Pipeline!I:I)+SUMIF(Pipeline!H:H,"Commercials",Pipeline!I:I)
A16: Total Pipeline (excl. Lost) | B16: =B14+B15
A17: Average Deal Size | B17: =IFERROR(C11/B11,0)
A18: Deals with TBD Costs | B18: =COUNTIF(Pipeline!I:I,"TBD")
A20: TEAM PERFORMANCE
A21: Team Member | B21: Total Deals | C21: Closed | D21: Closing Rate | E21: Revenue
A22: Tan | B22: =COUNTIF(Pipeline!D:D,"Tan") | C22: =COUNTIFS(Pipeline!D:D,"Tan",Pipeline!H:H,"Closed") | D22: =IFERROR(C22/B22,0) | E22: =SUMIFS(Pipeline!I:I,Pipeline!D:D,"Tan",Pipeline!H:H,"Closed")
A23: Ally | B23: =COUNTIF(Pipeline!D:D,"Ally") | C23: =COUNTIFS(Pipeline!D:D,"Ally",Pipeline!H:H,"Closed") | D23: =IFERROR(C23/B23,0) | E23: =SUMIFS(Pipeline!I:I,Pipeline!D:D,"Ally",Pipeline!H:H,"Closed")
A25: SCOPE TYPE BREAKDOWN
A26: Scope Type | B26: Count | C26: Value
A27: Branding | B27: =COUNTIF(Pipeline!C:C,"*Branding*") | C27: =SUMIF(Pipeline!C:C,"*Branding*",Pipeline!I:I)
A28: Web | B28: =COUNTIF(Pipeline!C:C,"*Web*") | C28: =SUMIF(Pipeline!C:C,"*Web*",Pipeline!I:I)
A29: SMM | B29: =COUNTIF(Pipeline!C:C,"*SMM*") | C29: =SUMIF(Pipeline!C:C,"*SMM*",Pipeline!I:I)
A30: Campaign | B30: =COUNTIF(Pipeline!C:C,"*Campaign*") | C30: =SUMIF(Pipeline!C:C,"*Campaign*",Pipeline!I:I)
A31: Creatives | B31: =COUNTIF(Pipeline!C:C,"*Creatives*") | C31: =SUMIF(Pipeline!C:C,"*Creatives*",Pipeline!I:I)
A32: Coffee table Book | B32: =COUNTIF(Pipeline!C:C,"*Coffee table Book*") | C32: =SUMIF(Pipeline!C:C,"*Coffee table Book*",Pipeline!I:I)

Sheet Closed Deals
A1: Date | B1: Brand Name | C1: Type of Scope | D1: Handled by | E1: POC Name | F1: Phone | G1: Email | H1: Stage | I1: Costs | J1: Proposal Date/Follow up | K1: Status
B2: Restaurant | C2: Branding | D2: Ally | E2: Ashwin | F2: +91 73027 39698 | G2: ashwin2002singh@gmail.com | H2: Closed | I2: 120000000 | K2: Closed. Awaiting advance payment, client has mentioned that is in process.
B3: Sweet Dreams | C3: Branding | D3: Ally | E3: Khushi | F3: +91 98709 10111 | G3: khushi.apwig@gmail.com | H3: Closed | I3: 100000000 | K3: Contract needs to be shared
B4: Pepsodent | C4: Branding | D4: Tan | E4: Reshma | F4: +91 99302 99445 | G4: reshma.vaidya@unilever.com | H4: Closed | I4: 100000000 | K4: Project completed.
B5: Stationery Brand | C5: Branding | D5: Ally | E5: Radhika | F5: +91 88894 44400 | G5: radhika@krishnaunited.com | H5: Closed | I5: 50000000 | K5: Branding proposal closed.
B6: Ageasy | C6: Branding | D6: Ally | E6: Arushi | F6: +91 90134 92656 | G6: arushi.aggarwal@antaraseniorcare.com | H6: Closed | I6: 40000000 | K6: Proposal shared with the client for review and approval
B7: KSM Ashwagandha | C7: Branding, Web | D7: Tan | E7: Kartikeya | F7: +91 98490 30798 | G7: kartikeya@ixoreal.com | H7: Closed | I7: 32500000 | K7: Project completed.
B8: Hamleys Cafe | C8: Campaign | D8: Ally | E8: Bala | F8: +91 98209 64012 | G8: sivaraman.B@ril.com | H8: Closed | I8: 20000000 | K8: Hamleys Cafe Logo and Guidelines
B9: Dove | C9: Branding | D9: Tan | E9: Manasee | F9: +91 98676 42764 | G9: manasee.naik@unilever.com | H9: Closed | I9: 15000000 | K9: Project completed
B10: Pears | C10: Branding | D10: Tan | E10: Manasee | F10: +91 98676 42764 | G10: manasee.naik@unilever.com | H10: Closed | I10: 15000000 | K10: Project completed

Sheet Active Pipeline
A1: Date | B1: Brand Name | C1: Type of Scope | D1: Handled by | E1: POC Name | F1: Phone | G1: Email | H1: Stage | I1: Costs | J1: Proposal Date/Follow up | K1: Status
B2: CtrlS | C2: Branding | D2: Ally | E2: Pragun | F2: +91 93729 10823 | G2: pragun.narang@ctrls.in | H2: Commercials | I2: 350000000 | K2: Client will update us on 14th August since he is on leave.
B3: Switchback | C3: Branding | D3: Ally | E3: Anushri | F3: +91 98198 77308 | G3: anushri20@gmail.com | H3: Commercials | I3: 150000000 | K3: This is cold atm
B4: Ride Glyde | C4: Branding | D4: Ally | E4: Vignesh | F4: +91 91369 60544 | G4: vignesh@rideglyde.in | H4: Commercials | I4: 150000000 | K4: Client pushing marketing a bit for now, focusing on finalising operations.
B5: Kimirica | C5: Branding | D5: Ally | E5: Saomya | F5: +91 98930 60926 | G5: soamya.mital@kimirica.com | H5: Commercials | I5: 150000000 | K5: On hold atm
B6: KKings Events | C6: Branding | D6: Ally | E6: Ketan | G6: ketan@kkingsevents.com | H6: Commercials | I6: 130000000 | K6: Proposal shared client to revert on the same.
B7: Nilambari Sarees | C7: Branding, Web | D7: Tan | E7: Pranav | F7: +91 88004 77886 | G7: pranavnilambari@gmail.com | H7: Commercials | I7: 120000000 | K7: He ghosted us.
B8: Sports Nutrition Brand | C8: Branding | D8: Ally | E8: Shabnam | F8: +91 97268 82211 | G8: Shabnamhalani8@gmail.com | H8: Commercials | I8: 115000000 | K8: Follow up done client will get back post the long weekend
B9: Speedex | C9: Branding | D9: Ally | E9: Dewakar | F9: +91 99112 02317 | G9: brandmarketer@speedexind.com | H9: Commercials | I9: 100000000 | K9: Pitch on 26th August
A10: 12th Feb | B10: Organic Food Brand | C10: Branding | D10: Tan | E10: Yashraj | F10: +91 96986 91111 | G10: yashrajsinghtada@gmail.com | H10: First Call | I10: 100000000 | K10: Yashraj has a budget of 7L for branding and packaging.
A11: 11th March | B11: Fabletics | C11: Branding | D11: Tan | E11: Roshni | F11: +91 95799 39636 | H11: Commercials | I11: 30000000 | K11: Need to send the proposal today.
A12: 22nd Jan | B12: Project Ezza | C12: Branding, Web | D12: Ally | E12: Dimpy | F12: +91 99202 74266 | H12: Commercials | I12: 550000 | K12: Proposal has been shared with the client for website.
B13: Scapes Hospitality | C13: SMM, Web | D13: Tan | E13: Aastha | F13: +91 81300 01729 | G13: aastha@scapeshospitality.com | H13: Commercials | K13: Project was on hold.
B14: Pantaloons | C14: Branding | D14: Ally | E14: Namit | F14: +91 88795 02010 | G14: namit.jaiswal@abfrl.adityabirla.com | H14: Pitch | I14: TBD | K14: Rate card has been shared with the client. Client to get back
B15: XOBO | C15: Branding | D15: Ally | E15: Kunal | F15: +91 99601 00100 | G15: kunaljain.vega@gmail.com | H15: Pitch | K15: Proposal under review.
B16: Komyo Wellness | C16: Web | D16: Ally | E16: Aditi | F16: +91 98110 29230 | G16: aditi@Komyo.in | H16: Commercials | K16: Client to get back on the proposal
B17: Kaafi Machine | C17: Branding | D17: Ally | E17: Anurag | G17: anurag.das@kaapimachines.com | H17: Pitch | I17: TBD | K17: Anurag to get back on the call timing
B18: House of Swadehi | C18: Branding | D18: Ally | G18: houseofswadeshiofficial@gmail.com | H18: First Call | I18: TBD | K18: Have requested for a call time to discuss the Logo development project.
B19: Saanya | C19: Web | D19: Ally | F19: +91 93100 00663 | G19: saanyabjain@gmail.com | H19: First Call | I19: TBD | K19: She wants to see the backend work on the developer
B20: Ruloans | C20: Campaign | D20: Ally | E20: Shikha | G20: shikha.mehta@ruloans.com | H20: Commercials | I20: TBD | K20: In-person meet at the client office
B21: Humane World For Animals | C21: Creatives | D21: Ally | E21: Shreya | F21: +91 63589 13490 | G21: sswaminath@humaneworld.org | H21: First Call | I21: TBD | K21: revised proposal to be shared for print and outdoor
B22: Anahata | D22: Ally | E22: Cecilia | F22: +91 98205 33332 | G22: admin@anahata.in | H22: First Call | K22: she will call back
B23: Sambhav Group | C23: Web | D23: Tan | E23: Megha | F23: +91 90049 86631 | G23: media@sambhavgroup.co.in | H23: Commercials | K23: Project was on hold.
B24: Cool Planet | C24: Branding | D24: Ally | E24: Rizqi | F24: +94777653936 | G24: qi@coolplanet.lk | H24: Commercials | I24: TBD
B25: Voltas | C25: Branding | D25: Tan | E25: Gayathri | F25: +91 96006 56773 | G25: gayathrinarendran@voltas.com | H25: First Call | K25: Client ghosted us.
B26: A Class Marble | C26: Web | D26: Tan | E26: Shivani | F26: +91 72900 73527 | G26: branding@aclassmarble.co.in | H26: Commercials | K26: Project on hold
B27: Rameswaram cafe | C27: Branding | D27: Tan | E27: Pooja | F27: +91 89281 91088 | G27: pooja.u@seabird.co.in | H27: Commercials | K27: They ghosted us.
B28: Sony Music | C28: Branding | D28: Ally | E28: Samarth | F28: +91 77220 36793 | G28: samarth.manocha@sonymusic.com | H28: Commercials | K28: Proposal shared. Client to get back
B29: ECCO | C29: Branding | D29: Ally | E29: Inza | F29: +91 96193 40027 | G29: INN@ecco.com | H29: Commercials | K29: Revised proposal discussion to happen basis the deliverables requested by the client.
B30: Upadhyaya Foundation | C30: Branding | D30: Ally | E30: Preetham | F30: +91 94837 80058 | G30: preetham@upadhyayafoundation.org | H30: Commercials | K30: Proposal shared with the client.
B31: Dainik Bhaskar Pet Care | C31: Branding | D31: Tan | E31: Diva | F31: - | G31: diva@dbdigital.in | H31: First Call | K31: Ghosted us because of commercials I guess
B32: Everfruit | C32: Branding | D32: Ally | E32: Piyush | F32: +91 95616 21164 | G32: piyush.parakh@everfruit.in | H32: Commercials | K32: Proposal shared with the client.
B33: Big FM | C33: Branding | D33: Ally | E33: Soha | F33: +91 99905 90444 | G33: akanksha.goel@weinvert.com | H33: Commercials | K33: RFP shared with the client.
B34: Amaya | C34: Web | D34: Ally | E34: Akshi | F34: +91 96431 22358 | G34: aakshi.katyal@gmail.com | H34: Commercials | K34: Proposal and pitch for the 24th October.
B35: Peruh | C35: Branding | D35: Tan | E35: Prerna | G35: prerna@peruhworld.com | H35: First Call | K35: Ghosted us
B36: Jawa | C36: Branding | D36: Ally | E36: Samir Gokhale | F36: +91 99210 03800 | G36: gokhale.samir@classiclegends.com | H36: First Call | K36: Blueprint to be shared with the client basis the last pitch
B37: Volfsbane | C37: Web | D37: Ally | E37: Mansi | G37: mansi@volfsbane.com | H37: Commercials | K37: Website branding proposal shared. Awaiting response.
B38: Asian Star | C38: Branding | D38: Ally | E38: Ryan | F38: +91 98205 07257 | G38: ryan@asianstargroup.com | H38: First Call | K38: CTR back on the proposal shared
B39: Samarya | C39: Branding | D39: Ally | E39: Aryan | F39: +91 91378 09177 | G39: aryan.ruia@samaryamedia.com | H39: Commercials | K39: Logo Design Proposal shared with the client.
B40: Seedwater | C40: Branding | D40: Ally | E40: Vivek | F40: +91 98197 11218 | G40: vivek@seedwtr.com | H40: Commercials | K40: CTR on the proposal shared
B41: Quartroloom | C41: Branding | D41: Ally | E41: Avase | F41: +91 88676 58800 | G41: avase@quartoloom.com | H41: Commercials | K41: CTR on the proposal shared
B42: Rajhem Jewellers | C42: Branding | D42: Ally | E42: Ritik | F42: +91 95153 11755 | G42: ritikjain23112@gmail.com | H42: Commercials | K42: CTR on the proposal shared
B43: Wellness Brand | C43: Branding | D43: Ally | E43: Ruchi | F43: +91 73508 89295 | G43: ruchi.pandit2008@gmail.com | H43: Commercials | K43: Client will get back with the numbers they want to close on today.
B44: O Source Global | C44: Web | D44: Tan | E44: Durvanka | F44: +91 96194 33680 | G44: durvanka.murkute@osourceglobal.com | H44: Commercials | K44: Commercials didn't work
B45: EuroKids | C45: Web | D45: Tan | E45: Rakesh | F45: +91 97737 73230 | G45: rakesh.baikar@lighthouse-learning.com | H45: Commercials | K45: Ghosted us
B46: Sanjeev (Healthy Snacks) | C46: Branding | D46: Ally | E46: Sanjeev | F46: +91 98153 38888 | G46: sb@sbhind.com | H46: First Call | K46: Proposal under review.
B47: Worthvial | C47: Branding | D47: Ally | E47: Rohit | F47: +91 90132 32346 | G47: rohit@worthvial.com | H47: Commercials | K47: Client will get back with the numbers they want to close on today.
B48: Bellagio | C48: Branding | D48: Ally | E48: Arya | F48: +91 90132 32346 | G48: aryaadak2000@gmail.com | H48: Commercials | K48: Client meeting on the 12th Jan, 2026
B49: Granotone | C49: Branding | D49: Tan | E49: Sarthak | F49: +91 97600 32125 | G49: sarthak@granotone.com | H49: Commercials | K49: Ghosted us.
B50: Nuvoco | C50: Branding | D50: Ally | E50: Nikhil | F50: +91 97020 36462 | G50: Nikhil.Sukthankar@nuvoco.com | H50: Pitch | K50: Pitch done. RFQ will be shared with us this week.
B51: Kids Infotainment | C51: Branding | D51: Tan | E51: Mazahir | F51: +91 90221 22928 | H51: First Call | K51: He ghosted us
B52: Cello | C52: Branding | D52: Ally | E52: Suresh | G52: suresh.amarnani@celloworld.com | H52: Commercials | K52: Proposal has been shared. No response.
A53: 14th Jan | B53: HueTag | C53: Branding | D53: Tan | E53: Yash | F53: +91 96436 34608 | G53: Yash.lakhmani0580@gmail.com | H53: First Call | K53: commercials didn't work
B54: Forge Tech | C54: Branding | D54: Ally | E54: Prasad | F54: +91 72084 82730 | G54: prasad.kabadi@ideaforgetech.com | H54: First Call | I54: TBD | K54: Tried connecting with the client but was not able to get through.
B55: Punjas | C55: Branding | D55: Ally | E55: Gopal | F55: +91 67970 08805 | G55: gopal@punjas.com | H55: Commercials | K55: Rate card shared with the client.
B56: NA | C56: Branding | D56: Tan | E56: Falguni | F56: +91 88799 27537 | G56: falguni240396@gmail.com | H56: Commercials | K56: commercials didn't work
B57: Biorad | C57: Branding | D57: Ally | E57: Tanishq | F57: +610451991409 | G57: tanishq.hegde@bioradmedisys.com | H57: First Call | K57: Proposal commercials closure call at 1 pm.
A58: 29th Jan | B58: Pureforma | C58: Branding | D58: Ally | E58: Pratima | F58: +91 98929 02338 | G58: pratima.kamat@pureforma.in | H58: First Call | K58: First call done with the client.
B59: Oilmax | C59: Branding | D59: Ally | E59: Rostan | F59: +91 99602 87807 | G59: rostan.miranda@aniritventures.com | H59: Commercials | K59: Proposal has been shared with the client. Awaiting response on the same.
B60: Kimora | C60: Branding | D60: Ally | E60: Bhumi | F60: +91 95100 70153 | G60: business@kimora.in | H60: Commercials | K60: Internal review of budgets ongoing.
A61: 12th Feb | B61: Coffee Branding | C61: Branding | D61: Tan | E61: Shreyansh | F61: +91 99872 48272 | G61: doshi.shreyansh@gmail.com | H61: Commercials | K61: Sent him a proposal for 22L, awaiting to hear back
A62: 16th Feb | B62: Automobile brand | C62: Branding | D62: Tan | E62: Dhrumil | F62: +91 91670 76010 | G62: dhrumil@dhcindia.com | H62: Commercials | K62: Have sent him our commercials
A63: 17th Feb | B63: SBI MF | C63: Creatives | D63: Tan | E63: Prachi | F63: +91 95994 07143 | G63: prachi.shinde@sbimf.com | H63: First Call
A64: 17th Feb | B64: Powerbuild Batteries | C64: Branding | D64: Ally | E64: Pawan | F64: +91 89833 50003 | G64: pawan.lahane@timetechnoplast.com | H64: Commercials | K64: Proposal shared for review. Awaiting response on the same.
A65: 18th Feb | B65: Kimirica | C65: Branding | D65: Ally | E65: Pooja | F65: +91 95840 00357 | G65: pooja.bhagat@kimirica.shop | H65: Commercials | K65: Mall Pop Up Moodboard commercials shared with the client. No response.
A66: 2nd March | B66: Ayvens India | C66: Branding | D66: Ally | E66: Shalini | F66: +91 95822 14969 | G66: shalini.baveja@ayvens.com | H66: Pitch | K66: Pitch date to be finalised basis the call.
A67: 2nd March | B67: Kimirica | C67: Web | D67: Ally | E67: Saloni | F67: +91 91117 44744 | G67: saloni.saraf@kimirica.shop | H67: Commercials | K67: Proposal shared with the client.
A68: 9th March | B68: Kalatita + NGO | C68: Branding | D68: Ally | E68: Darayash | F68: +91 98200 60818 | G68: darayash.gocal@gmail.com | H68: First Call | K68: Client is yet to confirm on the meeting in-office.

Sheet Lost Deals
A1: Date | B1: Brand Name | C1: Type of Scope | D1: Handled by | E1: POC Name | F1: Phone | G1: Email | H1: Stage | I1: Costs | J1: Proposal Date/Follow up | K1: Status
B2: Messe Muenchen | C2: Branding | D2: Ally | E2: Riddhi | F2: +91 75179 98999 | G2: support.marcom@mm-india.in | H2: Didnt work out | I2: 180000000 | K2: Client is not responding
B3: The Premium Basket | C3: Branding | D3: Ally | E3: Ebrahim Kothari | F3: +91 88281 92685 | G3: ebrahim@thepremiumbasket.com | H3: Didnt work out | I3: 167500000 | K3: We've shared the signed NDA with the client
B4: Bongchie | C4: Branding | D4: Ally | E4: Tushar | F4: +91 94547 48677 | G4: tushar@bongchie.com | H4: Didnt work out | I4: 140000000 | K4: Follow up done on the 1st July. No response. Awaiting a response.
B5: Miss Claire | C5: Branding | D5: Ally | E5: Mallika Ahar | F5: Not available | H5: Didnt work out | I5: 122500000 | K5: SPOC has been unresponsive.
B6: Raindus Beauty Care | C6: Branding | D6: Ally | E6: Saumya | F6: +91 78019 04359 | G6: admin@eurekacosmo.com | H6: Didnt work out | I6: 122500000 | K6: Branding proposal shared.
B7: Un'layered | C7: Branding | D7: Ally | E7: Bhawna | F7: +91 95282 55005 | G7: bhawnasharmaofficial@gmail.com | H7: Didnt work out | I7: 100000000 | K7: Call to be made on 2nd July 2025.
B8: HOF | C8: Branding | D8: Ally | E8: Somendra | F8: +91 99043 04513 | G8: somendra@hofindia.com | H8: Didnt work out | I8: 90000000 | K8: Branding proposal shared. Client is reviewing it at their end
B9: Vanveda Organics | C9: Branding | D9: Ally | E9: Chandan | F9: +91 75179 98999 | G9: support.marcom@mm-india.in | H9: Didnt work out | I9: 85000000 | K9: Update to be received by this weekend. 9-10th August
B10: Multichem | C10: Branding | D10: Ally | E10: Sejal Jadiyar | F10: +91 77382 47802 | G10: hello@multichemindia.com | H10: Didnt work out | I10: 74500000 | K10: Awaiting an update from the founder.
B11: Zydus Cadila | C11: Branding | D11: Tan | E11: Yash | F11: +91 98697 31997 | G11: YASHL.GANDHI@zyduslife.com | H11: Didnt work out | I11: 70000000 | K11: They ghosted us.
B12: Unomax | C12: Branding | D12: Ally | E12: Sajad | G12: sajjad.godhrawala@unomaxpens.com | H12: Didnt work out | I12: 50000000 | K12: Closed on an industrial design agency
B13: Cafe Branding | C13: Branding | D13: Ally | E13: Sharon | F13: +91 99306 56794 | G13: sharon22193@gmail.com | H13: Didnt work out | I13: 50000000 | K13: Branding proposal shared. Client is reviewing it at their end
B14: Food Brand Launch | C14: Branding | D14: Tan | E14: Akshay | F14: +91 98338 14029 | H14: Didnt work out | I14: - | K14: Didnt work out because of costs.
B15: Welspun | C15: Branding | D15: Ally | E15: Alok | F15: +91 99980 03155 | G15: Alok_Bhinde@welspun.com | H15: Didnt work out | K15: Client has said that CMO is travelling and this will take sometime to close on.
B16: South Indian Restaurant | C16: Branding | D16: Ally | E16: Shashank | F16: +91 88252 02574 | G16: shashanksauravv@gmail.com | H16: Didnt work out | I16: TBD | K16: Client will call back
B17: Indo Atma | C17: Branding | D17: Ally | E17: Arastu | F17: +5617597364 | G17: arastu@indoatma.com | H17: Didnt work out | K17: Client has gone silent on the NDA front.
B18: Dynamic Engineering | C18: Branding | D18: Ally | E18: Sehej | F18: +91 99305 64146 | G18: info@dynamicengineeringcompany.com | H18: Didnt work out | K18: Cost of 3L
B19: Ice Cream Brand | C19: Branding | D19: Ally | E19: Dharmesh | F19: +91 79074 87352 | G19: hnmpltd@outlook.com | H19: Didnt work out | K19: Budget of 2L
B20: Hindustan Times | C20: Branding | D20: Ally | E20: Srashti | F20: +91 87178 78891 | G20: srashti.jain@hindustantimes.com | H20: Didnt work out | K20: Badge and Trophy design costing shared with the client.
B21: Pump Manufacturer | C21: Branding | D21: Ally | E21: Nik | F21: +3468528114 | G21: nikp09528@gmail.com | H21: Didnt work out | K21: CTR on the proposal shared
B22: Haldirams | C22: Branding | D22: Ally | E22: Bhagyashree | F22: +91 96193 42495 | G22: bhagyashree.paralkar@haldirams.com | H22: Didnt work out | K22: Proposal to be shared post closure on social media
B23: Zune Clothing | C23: Branding | D23: Tan | E23: Shivam | F23: +91 75056 43933 | G23: shivamyadav9258@gmail.com | H23: Didnt work out | K23: Had very low budgets, 2L for branding.
B24: Luxury Bags | C24: Branding | D24: Ally | E24: Ayesha | F24: +91 96190 77701 | G24: NA | H24: Didnt work out | K24: Low budget client.
B25: HOS Global Foods | C25: Branding | D25: Ally | E25: Shruti | F25: +91 88794 33104 | G25: skulkarni@houseofspicesindia.com | H25: Didnt work out | K25: Client has mentioned they will work on future projects with us.
B26: Els Hair | C26: Web | D26: Ally | E26: Simran | F26: +91 83830 08876 | G26: work.skataria@gmail.com | H26: Didnt work out | K26: No response post proposal for website revamp shared with the client.
B27: Inorbit | C27: Branding | D27: Ally | E27: Tiyasha | F27: +91 96741 19228 | G27: tiyasha.mitra@inorbit.in | H27: Didnt work out | K27: Case Studies deck shared with the client.
A28: 19th Jan | B28: Oral-care FMCG brand | C28: Branding | D28: Ally | E28: Harshleen | F28: +91 95751 00999 | G28: bhatiaharshleen11@gmail.com | H28: Didnt work out | I28: TBD | K28: Client has not responded to calls and texts.
B29: Elevator Brand | C29: Branding | D29: Ally | E29: Prachi | F29: +91 77383 87212 | G29: prachi.jadhav@eroselevators.com | H29: Didnt work out | I29: TBD | K29: Commercials shared with the client. Client has not responded thereafter.
A30: 28th Jan | B30: My Athlete | C30: Branding | D30: Ally | E30: Bhaben | F30: +91 97926 74222 | G30: bhaben83@gmail.com | H30: Didnt work out | I30: TBD | K30: Proposal to be shared for the same by the 29th January, 2026
A31: 18th Feb | B31: Dada Design | C31: Web | D31: Ally | E31: Vasanthan | F31: +97451386864 | G31: vasanth@dadaarchitecture.com | H31: Didnt work out | K31: No response. Follow up has been done.
A32: 2nd March | B32: Upal - Branding | C32: Branding | D32: Ally | E32: Upal | F32: +91 98201 73037 | G32: upalsarkar31@gmail.com | H32: Didnt work out | K32: Budget of 2.5L.
A33: 2nd March | B33: Megrove Global School | C33: Branding | D33: Ally | E33: Amol | F33: +91 90214 96479 | G33: amol.m@adccacademy.com | H33: Didnt work out | K33: Proposal discussion and commercials on the 25th Feb.
